LICENSE.txt
README.md
setup.py
baumeva/__init__.py
baumeva/binary_ga.py
baumeva/categorical_ga.py
baumeva/collector_ga.py
baumeva/combinatory_ga.py
baumeva/ffga.py
baumeva/global_generator.py
baumeva/vega.py
baumeva.egg-info/PKG-INFO
baumeva.egg-info/SOURCES.txt
baumeva.egg-info/dependency_links.txt
baumeva.egg-info/top_level.txt
baumeva/ga/__init__.py
baumeva/ga/ga_data.py
baumeva/ga/multi_ga_data.py
baumeva/ga/multi_new_generation.py
baumeva/ga/new_generation.py
baumeva/ga/crossovers/__init__.py
baumeva/ga/crossovers/base_crossover.py
baumeva/ga/crossovers/one_point_crossover.py
baumeva/ga/crossovers/order_crossover.py
baumeva/ga/crossovers/two_point_crossover.py
baumeva/ga/crossovers/uniform_crossover.py
baumeva/ga/fitness/__init__.py
baumeva/ga/fitness/base_fitness.py
baumeva/ga/fitness/ffga_fitness.py
baumeva/ga/fitness/hyperbola_fitness.py
baumeva/ga/fitness/multi_fitness.py
baumeva/ga/fitness/vega_hyperbola_fitness.py
baumeva/ga/mutations/__init__.py
baumeva/ga/mutations/base_combinatory_mutation.py
baumeva/ga/mutations/base_mutation.py
baumeva/ga/mutations/bin_string_mutation.py
baumeva/ga/mutations/categorical_mutation.py
baumeva/ga/mutations/inversion_mutation.py
baumeva/ga/mutations/movement_mutation.py
baumeva/ga/mutations/shift_mutation.py
baumeva/ga/mutations/swap_mutation.py
baumeva/ga/penalties/__init__.py
baumeva/ga/penalties/adaptive_penalty.py
baumeva/ga/penalties/base_penalty.py
baumeva/ga/penalties/dynamic_penalty.py
baumeva/ga/penalties/static_penalty.py
baumeva/ga/populations/__init__.py
baumeva/ga/populations/base_population.py
baumeva/ga/populations/binary_gray_population.py
baumeva/ga/populations/binary_population.py
baumeva/ga/populations/cat_population.py
baumeva/ga/populations/order_cat_population.py
baumeva/ga/selections/__init__.py
baumeva/ga/selections/balanced_selection.py
baumeva/ga/selections/base_selection.py
baumeva/ga/selections/ranked_selection.py
baumeva/ga/selections/tournament_selection.py
baumeva/ga/selections/vega_balanced_selection.py
baumeva/ga/selections/vega_ranked_selection.py
baumeva/ga/selections/vega_tournament_selection.py